nys_constants/__init__.py
nys_constants/eta_coefficients.py
nys_constants/nys_constants.py
nys_constants-0.1.0.dist-info/licenses/LICENSE
nys_constants-0.1.0.dist-info/METADATA
nys_constants-0.1.0.dist-info/WHEEL
nys_constants-0.1.0.dist-info/top_level.txt
nys_constants-0.1.0.dist-info/RECORD
